bagpipe/__init__.py
bagpipe/main.py
bagpipe-0.0.1.dist-info/LICENSE
bagpipe-0.0.1.dist-info/METADATA
bagpipe-0.0.1.dist-info/WHEEL
bagpipe-0.0.1.dist-info/entry_points.txt
bagpipe-0.0.1.dist-info/top_level.txt
bagpipe-0.0.1.dist-info/RECORD
